fitb/__init__.py
fitb/extension.py
fitb/extension_point.py
fitb/loading.py
fitb/option.py
fitb/profile.py
fitb/utilities.py
fitb/version.py
fitb-3.1.0.dist-info/LICENSE
fitb-3.1.0.dist-info/METADATA
fitb-3.1.0.dist-info/WHEEL
fitb-3.1.0.dist-info/top_level.txt
fitb-3.1.0.dist-info/RECORD
