Metadata-Version: 2.1
Name: fitb
Version: 3.1.0
Summary: Practical configuration system
Home-page: https://github.com/abingham/fitb
Author: Austin Bingham
Author-email: austin.bingham@gmail.com
License: MIT
Platform: any
Classifier: Development Status :: 3 - Alpha
Classifier: Operating System :: OS Independent
Classifier: Programming Language :: Python
Classifier: Programming Language :: Python :: 3 :: Only
Requires-Dist: stevedore
Provides-Extra: dev
Requires-Dist: bumpversion ; extra == 'dev'
Requires-Dist: twine ; extra == 'dev'
Provides-Extra: test
Requires-Dist: hypothesis ; extra == 'test'
Requires-Dist: pytest ; extra == 'test'
